{
    "building": true,
    "highway": {
        "included_values": {
            "services": true,
            "rest_area": true,
            "escape": true
        }
    },
    "natural": {
        "excluded_values": {
            "coastline": true,
            "cliff": true,
            "ridge": true,
            "arete": true,
            "tree_row": true
        }
    },
    "landuse": true,
    "waterway": {
        "included_values": {
            "riverbank": true,
            "dock": true,
            "boatyard": true,
            "dam": true
        }
    },
    "amenity": true,
    "leisure": true,
    "barrier": {
        "included_values": {
            "city_wall": true,
            "ditch": true,
            "hedge": true,
            "retaining_wall": true,
            "wall": true,
            "spikes": true
        }
    },
    "railway": {
        "included_values": {
            "station": true,
            "turntable": true,
            "roundhouse": true,
            "platform": true
        }
    },
    "area": true,
    "boundary": true,
    "man_made": {
        "excluded_values": {
            "cutline": true,
            "embankment": true,
            "pipeline": true
        }
    },
    "power": {
        "included_values": {
            "plant": true,
            "substation": true,
            "generator": true,
            "transformer": true
        }
    },
    "place": true,
    "shop": true,
    "aeroway": {
        "excluded_values": {
            "taxiway": true
        }
    },
    "tourism": true,
    "historic": true,
    "public_transport": true,
    "office": true,
    "building:part": true,
    "military": true,
    "ruins": true,
    "area:highway": true,
    "craft": true,
    "golf": true
}
